<annotation><folder>augmented_images</folder><filename>chicago_153.pdf_6.xml</filename><path>chicago_153.pdf_6.xml</path><size><width>1700</width><height>2200</height><depth>1</depth></size><object><name>signature</name><bndbox><xmin>71</xmin><xmax>531</xmax><ymin>1577</ymin><ymax>1789</ymax></bndbox></object><object><name>signature</name><bndbox><xmin>1071</xmin><xmax>1397</xmax><ymin>1609</ymin><ymax>1723</ymax></bndbox></object><object><name>signature</name><bndbox><xmin>61</xmin><xmax>440</xmax><ymin>1924</ymin><ymax>2004</ymax></bndbox></object></annotation>