<annotation><folder>augmented_images</folder><filename>chicago_482.pdf_13.xml</filename><path>chicago_482.pdf_13.xml</path><size><width>1707</width><height>2200</height><depth>1</depth></size><object><name>signature</name><bndbox><xmin>1029</xmin><xmax>1270</xmax><ymin>1757</ymin><ymax>1890</ymax></bndbox></object><object><name>signature</name><bndbox><xmin>237</xmin><xmax>488</xmax><ymin>1792</ymin><ymax>1885</ymax></bndbox></object><object><name>signature</name><bndbox><xmin>1119</xmin><xmax>1215</xmax><ymin>1901</ymin><ymax>1978</ymax></bndbox></object></annotation>