<annotation><folder>augmented_images</folder><filename>chicago_268.pdf_2.xml</filename><path>chicago_268.pdf_2.xml</path><size><width>1700</width><height>2200</height><depth>1</depth></size><object><name>signature</name><bndbox><xmin>252</xmin><xmax>562</xmax><ymin>1340</ymin><ymax>1439</ymax></bndbox></object><object><name>signature</name><bndbox><xmin>236</xmin><xmax>648</xmax><ymin>1646</ymin><ymax>1819</ymax></bndbox></object><object><name>signature</name><bndbox><xmin>493</xmin><xmax>713</xmax><ymin>1762</ymin><ymax>1975</ymax></bndbox></object></annotation>