<annotation><folder>augmented_images</folder><filename>chicago_223.pdf_43.xml</filename><path>chicago_223.pdf_43.xml</path><size><width>1717</width><height>2214</height><depth>1</depth></size><object><name>signature</name><bndbox><xmin>192</xmin><xmax>423</xmax><ymin>1848</ymin><ymax>1965</ymax></bndbox></object><object><name>signature</name><bndbox><xmin>951</xmin><xmax>1348</xmax><ymin>1852</ymin><ymax>1924</ymax></bndbox></object><object><name>signature</name><bndbox><xmin>961</xmin><xmax>1444</xmax><ymin>1940</ymin><ymax>2004</ymax></bndbox></object></annotation>