<annotation><folder>augmented_images</folder><filename>chicago_541.pdf_58.xml</filename><path>chicago_541.pdf_58.xml</path><size><width>1698</width><height>2206</height><depth>1</depth></size><object><name>signature</name><bndbox><xmin>749</xmin><xmax>1123</xmax><ymin>932</ymin><ymax>1115</ymax></bndbox></object><object><name>signature</name><bndbox><xmin>329</xmin><xmax>734</xmax><ymin>1411</ymin><ymax>1504</ymax></bndbox></object><object><name>signature</name><bndbox><xmin>117</xmin><xmax>643</xmax><ymin>1764</ymin><ymax>1891</ymax></bndbox></object></annotation>